agi/__init__.py
agi/api/__init__.py
agi/api/client.py
agi/api/consts.py
agi-0.2.1.dist-info/METADATA
agi-0.2.1.dist-info/WHEEL
agi-0.2.1.dist-info/top_level.txt
agi-0.2.1.dist-info/RECORD
