Metadata-Version: 2.4
Name: agi
Version: 0.2.1
Summary: A Python client library for interacting with the General Reasoning platform
Author-email: General Reasoning Team <hello@gr.inc>
License: MIT
Project-URL: Homepage, https://github.com/GeneralReasoning/agi
Requires-Python: >=3.7
Requires-Dist: requests>=2.31.0
